mct_quantizers/__init__.py
mct_quantizers/logger.py
mct_quantizers/common/__init__.py
mct_quantizers/common/base_inferable_quantizer.py
mct_quantizers/common/constants.py
mct_quantizers/common/get_all_subclasses.py
mct_quantizers/common/get_quantizers.py
mct_quantizers/common/metadata.py
mct_quantizers/common/quant_info.py
mct_quantizers/common/quant_utils.py
mct_quantizers/keras/__init__.py
mct_quantizers/keras/activation_quantization_holder.py
mct_quantizers/keras/load_model.py
mct_quantizers/keras/metadata.py
mct_quantizers/keras/quantize_wrapper.py
mct_quantizers/keras/quantizer_utils.py
mct_quantizers/keras/validation_functions.py
mct_quantizers/keras/quantizers/__init__.py
mct_quantizers/keras/quantizers/base_keras_inferable_quantizer.py
mct_quantizers/keras/quantizers/activation_inferable_quantizers/__init__.py
mct_quantizers/keras/quantizers/activation_inferable_quantizers/activation_lut_pot_inferable_quantizer.py
mct_quantizers/keras/quantizers/activation_inferable_quantizers/activation_pot_inferable_quantizer.py
mct_quantizers/keras/quantizers/activation_inferable_quantizers/activation_symmetric_inferable_quantizer.py
mct_quantizers/keras/quantizers/activation_inferable_quantizers/activation_uniform_inferable_quantizer.py
mct_quantizers/keras/quantizers/weights_inferable_quantizers/__init__.py
mct_quantizers/keras/quantizers/weights_inferable_quantizers/weights_lut_pot_inferable_quantizer.py
mct_quantizers/keras/quantizers/weights_inferable_quantizers/weights_lut_symmetric_inferable_quantizer.py
mct_quantizers/keras/quantizers/weights_inferable_quantizers/weights_pot_inferable_quantizer.py
mct_quantizers/keras/quantizers/weights_inferable_quantizers/weights_symmetric_inferable_quantizer.py
mct_quantizers/keras/quantizers/weights_inferable_quantizers/weights_uniform_inferable_quantizer.py
mct_quantizers/pytorch/__init__.py
mct_quantizers/pytorch/activation_quantization_holder.py
mct_quantizers/pytorch/fln_activation_quantization_holder.py
mct_quantizers_nightly-1.6.0.20250912.post11759.dist-info/LICENSE.md
mct_quantizers_nightly-1.6.0.20250912.post11759.dist-info/METADATA
mct_quantizers_nightly-1.6.0.20250912.post11759.dist-info/WHEEL
mct_quantizers_nightly-1.6.0.20250912.post11759.dist-info/top_level.txt
mct_quantizers_nightly-1.6.0.20250912.post11759.dist-info/RECORD
