Metadata-Version: 2.1
Name: mct-quantizers-nightly
Version: 1.6.0.20250912.post11759
Summary: Infrastructure for support neural networks compression
Author-email: ssi-dnn-dev@sony.com
Classifier: Programming Language :: Python :: 3
Classifier: License :: OSI Approved :: Apache Software License
Classifier: Operating System :: OS Independent
Classifier: Topic :: Scientific/Engineering :: Artificial Intelligence
Requires-Python: >=3.6
License-File: LICENSE.md
Requires-Dist: numpy
Requires-Dist: packaging
